dtwTH/__init__.py
dtwTH-0.1.dist-info/DESCRIPTION.rst
dtwTH-0.1.dist-info/METADATA
dtwTH-0.1.dist-info/RECORD
dtwTH-0.1.dist-info/WHEEL
dtwTH-0.1.dist-info/metadata.json
dtwTH-0.1.dist-info/top_level.txt
