Metadata-Version: 2.0
Name: dtwTH
Version: 0.1
Summary: Dynamic Time Warping Distance
Home-page: UNKNOWN
Author: Tom Hartvigsen
Author-email: twhartvigsen@wpi.edu
License: UNKNOWN
Platform: UNKNOWN
